{"siegfried":"1.9.0","scandate":"2020-10-24T07:39:12-04:00","signature":"default.sig","created":"2020-10-08T10:36:55-04:00","identifiers":[{"name":"wikidata","details":"wikidata-definitions-1.0.0 (2020-10-08)"}],"files":[{"filename":"C:\\users\\emc83\\temp\\39002087358793_D4\\39002087358793_D4","filesize": 733937664,"modified":"2015-11-18T08:09:19-05:00","errors": "","matches": [{"ns":"wikidata","id":"UNKNOWN","format":"","URI":"","mime":"","basis":"","source":"","warning":"no match"}]},{"filename":"C:\\users\\emc83\\temp\\39002087358793_D4\\AutoPlay\\Videos\\Library Technicians.mpeg","filesize": 15160828,"modified":"2006-01-11T10:24:16-05:00","errors": "","matches": [{"ns":"wikidata","id":"Q28018471","format":"MPEG-2 program stream","URI":"http://www.wikidata.org/entity/Q28018471","mime":"video/MP2P","basis":"extension match mpeg","source":"","warning":""},{"ns":"wikidata","id":"Q336284","format":"MPEG-1","URI":"http://www.wikidata.org/entity/Q336284","mime":"video/mpeg; audio/mpeg","basis":"extension match mpeg","source":"","warning":""},{"ns":"wikidata","id":"Q28018470","format":"MPEG-1 program stream","URI":"http://www.wikidata.org/entity/Q28018470","mime":"video/MP1S","basis":"extension match mpeg","source":"","warning":""}]},{"filename":"C:\\users\\emc83\\temp\\39002087358793_D4\\AutoPlay\\Videos\\Library assistants.mpeg","filesize": 16984400,"modified":"2006-01-11T10:23:44-05:00","errors": "","matches": [{"ns":"wikidata","id":"Q28018471","format":"MPEG-2 program stream","URI":"http://www.wikidata.org/entity/Q28018471","mime":"video/MP2P","basis":"extension match mpeg","source":"","warning":""},{"ns":"wikidata","id":"Q336284","format":"MPEG-1","URI":"http://www.wikidata.org/entity/Q336284","mime":"video/mpeg; audio/mpeg","basis":"extension match mpeg","source":"","warning":""},{"ns":"wikidata","id":"Q28018470","format":"MPEG-1 program stream","URI":"http://www.wikidata.org/entity/Q28018470","mime":"video/MP1S","basis":"extension match mpeg","source":"","warning":""}]},{"filename":"C:\\users\\emc83\\temp\\39002087358793_D4\\AutoPlay\\Videos\\Lifeguards.mpeg","filesize": 23077402,"modified":"2006-01-11T15:00:53-05:00","errors": "","matches": [{"ns":"wikidata","id":"Q28018471","format":"MPEG-2 program stream","URI":"http://www.wikidata.org/entity/Q28018471","mime":"video/MP2P","basis":"extension match mpeg","source":"","warning":""},{"ns":"wikidata","id":"Q336284","format":"MPEG-1","URI":"http://www.wikidata.org/entity/Q336284","mime":"video/mpeg; audio/mpeg","basis":"extension match mpeg","source":"","warning":""},{"ns":"wikidata","id":"Q28018470","format":"MPEG-1 program stream","URI":"http://www.wikidata.org/entity/Q28018470","mime":"video/MP1S","basis":"extension match mpeg","source":"","warning":""}]},{"filename":"C:\\users\\emc83\\temp\\39002087358793_D4\\AutoPlay\\Videos\\Locker room.mpeg","filesize": 19059124,"modified":"2006-01-11T15:01:14-05:00","errors": "","matches": [{"ns":"wikidata","id":"Q28018471","format":"MPEG-2 program stream","URI":"http://www.wikidata.org/entity/Q28018471","mime":"video/MP2P","basis":"extension match mpeg","source":"","warning":""},{"ns":"wikidata","id":"Q336284","format":"MPEG-1","URI":"http://www.wikidata.org/entity/Q336284","mime":"video/mpeg; audio/mpeg","basis":"extension match mpeg","source":"","warning":""},{"ns":"wikidata","id":"Q28018470","format":"MPEG-1 program stream","URI":"http://www.wikidata.org/entity/Q28018470","mime":"video/MP1S","basis":"extension match mpeg","source":"","warning":""}]},{"filename":"C:\\users\\emc83\\temp\\39002087358793_D4\\AutoPlay\\Videos\\Machinists.mpeg","filesize": 13006240,"modified":"2006-01-11T20:50:58-05:00","errors": "","matches": [{"ns":"wikidata","id":"Q28018471","format":"MPEG-2 program stream","URI":"http://www.wikidata.org/entity/Q28018471","mime":"video/MP2P","basis":"extension match mpeg","source":"","warning":""},{"ns":"wikidata","id":"Q336284","format":"MPEG-1","URI":"http://www.wikidata.org/entity/Q336284","mime":"video/mpeg; audio/mpeg","basis":"extension match mpeg","source":"","warning":""},{"ns":"wikidata","id":"Q28018470","format":"MPEG-1 program stream","URI":"http://www.wikidata.org/entity/Q28018470","mime":"video/MP1S","basis":"extension match mpeg","source":"","warning":""}]},{"filename":"C:\\users\\emc83\\temp\\39002087358793_D4\\AutoPlay\\Videos\\Maids.mpeg","filesize": 10988640,"modified":"2006-01-11T15:01:14-05:00","errors": "","matches": [{"ns":"wikidata","id":"Q28018471","format":"MPEG-2 program stream","URI":"http://www.wikidata.org/entity/Q28018471","mime":"video/MP2P","basis":"extension match mpeg","source":"","warning":""},{"ns":"wikidata","id":"Q336284","format":"MPEG-1","URI":"http://www.wikidata.org/entity/Q336284","mime":"video/mpeg; audio/mpeg","basis":"extension match mpeg","source":"","warning":""},{"ns":"wikidata","id":"Q28018470","format":"MPEG-1 program stream","URI":"http://www.wikidata.org/entity/Q28018470","mime":"video/MP1S","basis":"extension match mpeg","source":"","warning":""}]},{"filename":"C:\\users\\emc83\\temp\\39002087358793_D4\\AutoPlay\\Videos\\Mail clerk.mpg","filesize": 16219276,"modified":"2006-01-11T09:08:30-05:00","errors": "","matches": [{"ns":"wikidata","id":"Q28018471","format":"MPEG-2 program stream","URI":"http://www.wikidata.org/entity/Q28018471","mime":"video/MP2P","basis":"extension match mpg","source":"","warning":""},{"ns":"wikidata","id":"Q336284","format":"MPEG-1","URI":"http://www.wikidata.org/entity/Q336284","mime":"video/mpeg; audio/mpeg","basis":"extension match mpg","source":"","warning":""},{"ns":"wikidata","id":"Q28018470","format":"MPEG-1 program stream","URI":"http://www.wikidata.org/entity/Q28018470","mime":"video/MP1S","basis":"extension match mpg","source":"","warning":""}]},{"filename":"C:\\users\\emc83\\temp\\39002087358793_D4\\AutoPlay\\Videos\\Mail processing.mpeg","filesize": 17922246,"modified":"2006-01-11T11:50:12-05:00","errors": "","matches": [{"ns":"wikidata","id":"Q28018471","format":"MPEG-2 program stream","URI":"http://www.wikidata.org/entity/Q28018471","mime":"video/MP2P","basis":"extension match mpeg","source":"","warning":""},{"ns":"wikidata","id":"Q336284","format":"MPEG-1","URI":"http://www.wikidata.org/entity/Q336284","mime":"video/mpeg; audio/mpeg","basis":"extension match mpeg","source":"","warning":""},{"ns":"wikidata","id":"Q28018470","format":"MPEG-1 program stream","URI":"http://www.wikidata.org/entity/Q28018470","mime":"video/MP1S","basis":"extension match mpeg","source":"","warning":""}]},{"filename":"C:\\users\\emc83\\temp\\39002087358793_D4\\AutoPlay\\Videos\\Manicurists.mpeg","filesize": 15645760,"modified":"2006-01-11T21:22:02-05:00","errors": "","matches": [{"ns":"wikidata","id":"Q28018471","format":"MPEG-2 program stream","URI":"http://www.wikidata.org/entity/Q28018471","mime":"video/MP2P","basis":"extension match mpeg","source":"","warning":""},{"ns":"wikidata","id":"Q336284","format":"MPEG-1","URI":"http://www.wikidata.org/entity/Q336284","mime":"video/mpeg; audio/mpeg","basis":"extension match mpeg","source":"","warning":""},{"ns":"wikidata","id":"Q28018470","format":"MPEG-1 program stream","URI":"http://www.wikidata.org/entity/Q28018470","mime":"video/MP1S","basis":"extension match mpeg","source":"","warning":""}]},{"filename":"C:\\users\\emc83\\temp\\39002087358793_D4\\AutoPlay\\Videos\\Marketing Sales and Service.mpeg","filesize": 24348380,"modified":"2006-01-11T21:20:13-05:00","errors": "","matches": [{"ns":"wikidata","id":"Q28018471","format":"MPEG-2 program stream","URI":"http://www.wikidata.org/entity/Q28018471","mime":"video/MP2P","basis":"extension match mpeg","source":"","warning":""},{"ns":"wikidata","id":"Q336284","format":"MPEG-1","URI":"http://www.wikidata.org/entity/Q336284","mime":"video/mpeg; audio/mpeg","basis":"extension match mpeg","source":"","warning":""},{"ns":"wikidata","id":"Q28018470","format":"MPEG-1 program stream","URI":"http://www.wikidata.org/entity/Q28018470","mime":"video/MP1S","basis":"extension match mpeg","source":"","warning":""}]},{"filename":"C:\\users\\emc83\\temp\\39002087358793_D4\\AutoPlay\\Videos\\Miners.mpg","filesize": 14638290,"modified":"2006-01-10T12:24:11-05:00","errors": "","matches": [{"ns":"wikidata","id":"Q28018471","format":"MPEG-2 program stream","URI":"http://www.wikidata.org/entity/Q28018471","mime":"video/MP2P","basis":"extension match mpg","source":"","warning":""},{"ns":"wikidata","id":"Q336284","format":"MPEG-1","URI":"http://www.wikidata.org/entity/Q336284","mime":"video/mpeg; audio/mpeg","basis":"extension match mpg","source":"","warning":""},{"ns":"wikidata","id":"Q28018470","format":"MPEG-1 program stream","URI":"http://www.wikidata.org/entity/Q28018470","mime":"video/MP1S","basis":"extension match mpg","source":"","warning":""}]},{"filename":"C:\\users\\emc83\\temp\\39002087358793_D4\\AutoPlay\\Videos\\Motorcycle mechanics.mpeg","filesize": 15105454,"modified":"2006-01-11T21:56:05-05:00","errors": "","matches": [{"ns":"wikidata","id":"Q28018471","format":"MPEG-2 program stream","URI":"http://www.wikidata.org/entity/Q28018471","mime":"video/MP2P","basis":"extension match mpeg","source":"","warning":""},{"ns":"wikidata","id":"Q336284","format":"MPEG-1","URI":"http://www.wikidata.org/entity/Q336284","mime":"video/mpeg; audio/mpeg","basis":"extension match mpeg","source":"","warning":""},{"ns":"wikidata","id":"Q28018470","format":"MPEG-1 program stream","URI":"http://www.wikidata.org/entity/Q28018470","mime":"video/MP1S","basis":"extension match mpeg","source":"","warning":""}]},{"filename":"C:\\users\\emc83\\temp\\39002087358793_D4\\AutoPlay\\Videos\\Musicians instrumental.mpg","filesize": 11600160,"modified":"2006-01-11T00:11:56-05:00","errors": "","matches": [{"ns":"wikidata","id":"Q28018471","format":"MPEG-2 program stream","URI":"http://www.wikidata.org/entity/Q28018471","mime":"video/MP2P","basis":"extension match mpg","source":"","warning":""},{"ns":"wikidata","id":"Q336284","format":"MPEG-1","URI":"http://www.wikidata.org/entity/Q336284","mime":"video/mpeg; audio/mpeg","basis":"extension match mpg","source":"","warning":""},{"ns":"wikidata","id":"Q28018470","format":"MPEG-1 program stream","URI":"http://www.wikidata.org/entity/Q28018470","mime":"video/MP1S","basis":"extension match mpg","source":"","warning":""}]},{"filename":"C:\\users\\emc83\\temp\\39002087358793_D4\\AutoPlay\\Videos\\Musicians.mpg","filesize": 19463500,"modified":"2006-01-11T00:11:23-05:00","errors": "","matches": [{"ns":"wikidata","id":"Q28018471","format":"MPEG-2 program stream","URI":"http://www.wikidata.org/entity/Q28018471","mime":"video/MP2P","basis":"extension match mpg","source":"","warning":""},{"ns":"wikidata","id":"Q336284","format":"MPEG-1","URI":"http://www.wikidata.org/entity/Q336284","mime":"video/mpeg; audio/mpeg","basis":"extension match mpg","source":"","warning":""},{"ns":"wikidata","id":"Q28018470","format":"MPEG-1 program stream","URI":"http://www.wikidata.org/entity/Q28018470","mime":"video/MP1S","basis":"extension match mpg","source":"","warning":""}]},{"filename":"C:\\users\\emc83\\temp\\39002087358793_D4\\AutoPlay\\Videos\\Network administrators.mpeg","filesize": 20016144,"modified":"2006-01-11T17:01:25-05:00","errors": "","matches": [{"ns":"wikidata","id":"Q28018471","format":"MPEG-2 program stream","URI":"http://www.wikidata.org/entity/Q28018471","mime":"video/MP2P","basis":"extension match mpeg","source":"","warning":""},{"ns":"wikidata","id":"Q336284","format":"MPEG-1","URI":"http://www.wikidata.org/entity/Q336284","mime":"video/mpeg; audio/mpeg","basis":"extension match mpeg","source":"","warning":""},{"ns":"wikidata","id":"Q28018470","format":"MPEG-1 program stream","URI":"http://www.wikidata.org/entity/Q28018470","mime":"video/MP1S","basis":"extension match mpeg","source":"","warning":""}]},{"filename":"C:\\users\\emc83\\temp\\39002087358793_D4\\AutoPlay\\Videos\\Non-farm animal caretaker.mpg","filesize": 20473588,"modified":"2006-01-10T21:57:07-05:00","errors": "","matches": [{"ns":"wikidata","id":"Q28018471","format":"MPEG-2 program stream","URI":"http://www.wikidata.org/entity/Q28018471","mime":"video/MP2P","basis":"extension match mpg","source":"","warning":""},{"ns":"wikidata","id":"Q336284","format":"MPEG-1","URI":"http://www.wikidata.org/entity/Q336284","mime":"video/mpeg; audio/mpeg","basis":"extension match mpg","source":"","warning":""},{"ns":"wikidata","id":"Q28018470","format":"MPEG-1 program stream","URI":"http://www.wikidata.org/entity/Q28018470","mime":"video/MP1S","basis":"extension match mpg","source":"","warning":""}]},{"filename":"C:\\users\\emc83\\temp\\39002087358793_D4\\AutoPlay\\Videos\\Non-traditional.mpeg","filesize": 18064200,"modified":"2006-01-11T22:47:48-05:00","errors": "","matches": [{"ns":"wikidata","id":"Q28018471","format":"MPEG-2 program stream","URI":"http://www.wikidata.org/entity/Q28018471","mime":"video/MP2P","basis":"extension match mpeg","source":"","warning":""},{"ns":"wikidata","id":"Q336284","format":"MPEG-1","URI":"http://www.wikidata.org/entity/Q336284","mime":"video/mpeg; audio/mpeg","basis":"extension match mpeg","source":"","warning":""},{"ns":"wikidata","id":"Q28018470","format":"MPEG-1 program stream","URI":"http://www.wikidata.org/entity/Q28018470","mime":"video/MP1S","basis":"extension match mpeg","source":"","warning":""}]},{"filename":"C:\\users\\emc83\\temp\\39002087358793_D4\\AutoPlay\\Videos\\Nursery Workers.mpg","filesize": 14254240,"modified":"2006-01-10T12:25:23-05:00","errors": "","matches": [{"ns":"wikidata","id":"Q28018471","format":"MPEG-2 program stream","URI":"http://www.wikidata.org/entity/Q28018471","mime":"video/MP2P","basis":"extension match mpg","source":"","warning":""},{"ns":"wikidata","id":"Q336284","format":"MPEG-1","URI":"http://www.wikidata.org/entity/Q336284","mime":"video/mpeg; audio/mpeg","basis":"extension match mpg","source":"","warning":""},{"ns":"wikidata","id":"Q28018470","format":"MPEG-1 program stream","URI":"http://www.wikidata.org/entity/Q28018470","mime":"video/MP1S","basis":"extension match mpg","source":"","warning":""}]},{"filename":"C:\\users\\emc83\\temp\\39002087358793_D4\\AutoPlay\\Videos\\Nursing aides.mpeg","filesize": 15308800,"modified":"2006-01-11T14:00:43-05:00","errors": "","matches": [{"ns":"wikidata","id":"Q28018471","format":"MPEG-2 program stream","URI":"http://www.wikidata.org/entity/Q28018471","mime":"video/MP2P","basis":"extension match mpeg","source":"","warning":""},{"ns":"wikidata","id":"Q336284","format":"MPEG-1","URI":"http://www.wikidata.org/entity/Q336284","mime":"video/mpeg; audio/mpeg","basis":"extension match mpeg","source":"","warning":""},{"ns":"wikidata","id":"Q28018470","format":"MPEG-1 program stream","URI":"http://www.wikidata.org/entity/Q28018470","mime":"video/MP1S","basis":"extension match mpeg","source":"","warning":""}]},{"filename":"C:\\users\\emc83\\temp\\39002087358793_D4\\AutoPlay\\Videos\\OJT.mpeg","filesize": 20848216,"modified":"2006-01-11T22:47:11-05:00","errors": "","matches": [{"ns":"wikidata","id":"Q28018471","format":"MPEG-2 program stream","URI":"http://www.wikidata.org/entity/Q28018471","mime":"video/MP2P","basis":"extension match mpeg","source":"","warning":""},{"ns":"wikidata","id":"Q336284","format":"MPEG-1","URI":"http://www.wikidata.org/entity/Q336284","mime":"video/mpeg; audio/mpeg","basis":"extension match mpeg","source":"","warning":""},{"ns":"wikidata","id":"Q28018470","format":"MPEG-1 program stream","URI":"http://www.wikidata.org/entity/Q28018470","mime":"video/MP1S","basis":"extension match mpeg","source":"","warning":""}]},{"filename":"C:\\users\\emc83\\temp\\39002087358793_D4\\AutoPlay\\Videos\\Occupational therapy.mpg","filesize": 17130838,"modified":"2006-01-11T09:09:18-05:00","errors": "","matches": [{"ns":"wikidata","id":"Q28018471","format":"MPEG-2 program stream","URI":"http://www.wikidata.org/entity/Q28018471","mime":"video/MP2P","basis":"extension match mpg","source":"","warning":""},{"ns":"wikidata","id":"Q336284","format":"MPEG-1","URI":"http://www.wikidata.org/entity/Q336284","mime":"video/mpeg; audio/mpeg","basis":"extension match mpg","source":"","warning":""},{"ns":"wikidata","id":"Q28018470","format":"MPEG-1 program stream","URI":"http://www.wikidata.org/entity/Q28018470","mime":"video/MP1S","basis":"extension match mpg","source":"","warning":""}]},{"filename":"C:\\users\\emc83\\temp\\39002087358793_D4\\AutoPlay\\Videos\\Office clerks.mpg","filesize": 14029600,"modified":"2006-01-11T09:10:02-05:00","errors": "","matches": [{"ns":"wikidata","id":"Q28018471","format":"MPEG-2 program stream","URI":"http://www.wikidata.org/entity/Q28018471","mime":"video/MP2P","basis":"extension match mpg","source":"","warning":""},{"ns":"wikidata","id":"Q336284","format":"MPEG-1","URI":"http://www.wikidata.org/entity/Q336284","mime":"video/mpeg; audio/mpeg","basis":"extension match mpg","source":"","warning":""},{"ns":"wikidata","id":"Q28018470","format":"MPEG-1 program stream","URI":"http://www.wikidata.org/entity/Q28018470","mime":"video/MP1S","basis":"extension match mpg","source":"","warning":""}]},{"filename":"C:\\users\\emc83\\temp\\39002087358793_D4\\AutoPlay\\Videos\\Order fillers.mpeg","filesize": 15080836,"modified":"2006-01-11T21:22:15-05:00","errors": "","matches": [{"ns":"wikidata","id":"Q28018471","format":"MPEG-2 program stream","URI":"http://www.wikidata.org/entity/Q28018471","mime":"video/MP2P","basis":"extension match mpeg","source":"","warning":""},{"ns":"wikidata","id":"Q336284","format":"MPEG-1","URI":"http://www.wikidata.org/entity/Q336284","mime":"video/mpeg; audio/mpeg","basis":"extension match mpeg","source":"","warning":""},{"ns":"wikidata","id":"Q28018470","format":"MPEG-1 program stream","URI":"http://www.wikidata.org/entity/Q28018470","mime":"video/MP1S","basis":"extension match mpeg","source":"","warning":""}]},{"filename":"C:\\users\\emc83\\temp\\39002087358793_D4\\AutoPlay\\Videos\\Outdoor power.mpeg","filesize": 14221312,"modified":"2006-01-11T21:22:36-05:00","errors": "","matches": [{"ns":"wikidata","id":"Q28018471","format":"MPEG-2 program stream","URI":"http://www.wikidata.org/entity/Q28018471","mime":"video/MP2P","basis":"extension match mpeg","source":"","warning":""},{"ns":"wikidata","id":"Q336284","format":"MPEG-1","URI":"http://www.wikidata.org/entity/Q336284","mime":"video/mpeg; audio/mpeg","basis":"extension match mpeg","source":"","warning":""},{"ns":"wikidata","id":"Q28018470","format":"MPEG-1 program stream","URI":"http://www.wikidata.org/entity/Q28018470","mime":"video/MP1S","basis":"extension match mpeg","source":"","warning":""}]},{"filename":"C:\\users\\emc83\\temp\\39002087358793_D4\\AutoPlay\\Videos\\Packaging and Filling.mpeg","filesize": 0,"modified":"2006-01-11T20:51:21-05:00","errors": "empty source","matches": [{"ns":"wikidata","id":"Q28018471","format":"MPEG-2 program stream","URI":"http://www.wikidata.org/entity/Q28018471","mime":"video/MP2P","basis":"extension match mpeg","source":"","warning":""},{"ns":"wikidata","id":"Q336284","format":"MPEG-1","URI":"http://www.wikidata.org/entity/Q336284","mime":"video/mpeg; audio/mpeg","basis":"extension match mpeg","source":"","warning":""},{"ns":"wikidata","id":"Q28018470","format":"MPEG-1 program stream","URI":"http://www.wikidata.org/entity/Q28018470","mime":"video/MP1S","basis":"extension match mpeg","source":"","warning":""}]},{"filename":"C:\\users\\emc83\\temp\\39002087358793_D4\\AutoPlay\\Videos\\Painters.mpg","filesize": 0,"modified":"2006-01-10T22:43:55-05:00","errors": "empty source","matches": [{"ns":"wikidata","id":"Q28018471","format":"MPEG-2 program stream","URI":"http://www.wikidata.org/entity/Q28018471","mime":"video/MP2P","basis":"extension match mpg","source":"","warning":""},{"ns":"wikidata","id":"Q336284","format":"MPEG-1","URI":"http://www.wikidata.org/entity/Q336284","mime":"video/mpeg; audio/mpeg","basis":"extension match mpg","source":"","warning":""},{"ns":"wikidata","id":"Q28018470","format":"MPEG-1 program stream","URI":"http://www.wikidata.org/entity/Q28018470","mime":"video/MP1S","basis":"extension match mpg","source":"","warning":""}]},{"filename":"C:\\users\\emc83\\temp\\39002087358793_D4\\AutoPlay\\Videos\\Paperhangers.mpg","filesize": 0,"modified":"2006-01-10T22:44:37-05:00","errors": "empty source","matches": [{"ns":"wikidata","id":"Q28018471","format":"MPEG-2 program stream","URI":"http://www.wikidata.org/entity/Q28018471","mime":"video/MP2P","basis":"extension match mpg","source":"","warning":""},{"ns":"wikidata","id":"Q336284","format":"MPEG-1","URI":"http://www.wikidata.org/entity/Q336284","mime":"video/mpeg; audio/mpeg","basis":"extension match mpg","source":"","warning":""},{"ns":"wikidata","id":"Q28018470","format":"MPEG-1 program stream","URI":"http://www.wikidata.org/entity/Q28018470","mime":"video/MP1S","basis":"extension match mpg","source":"","warning":""}]},{"filename":"C:\\users\\emc83\\temp\\39002087358793_D4\\AutoPlay\\Videos\\Parking lot.mpeg","filesize": 0,"modified":"2006-01-11T15:01:34-05:00","errors": "empty source","matches": [{"ns":"wikidata","id":"Q28018471","format":"MPEG-2 program stream","URI":"http://www.wikidata.org/entity/Q28018471","mime":"video/MP2P","basis":"extension match mpeg","source":"","warning":""},{"ns":"wikidata","id":"Q336284","format":"MPEG-1","URI":"http://www.wikidata.org/entity/Q336284","mime":"video/mpeg; audio/mpeg","basis":"extension match mpeg","source":"","warning":""},{"ns":"wikidata","id":"Q28018470","format":"MPEG-1 program stream","URI":"http://www.wikidata.org/entity/Q28018470","mime":"video/MP1S","basis":"extension match mpeg","source":"","warning":""}]},{"filename":"C:\\users\\emc83\\temp\\39002087358793_D4\\AutoPlay\\Videos\\Personal and Home Care.mpeg","filesize": 0,"modified":"2006-01-11T16:34:28-05:00","errors": "empty source","matches": [{"ns":"wikidata","id":"Q28018471","format":"MPEG-2 program stream","URI":"http://www.wikidata.org/entity/Q28018471","mime":"video/MP2P","basis":"extension match mpeg","source":"","warning":""},{"ns":"wikidata","id":"Q336284","format":"MPEG-1","URI":"http://www.wikidata.org/entity/Q336284","mime":"video/mpeg; audio/mpeg","basis":"extension match mpeg","source":"","warning":""},{"ns":"wikidata","id":"Q28018470","format":"MPEG-1 program stream","URI":"http://www.wikidata.org/entity/Q28018470","mime":"video/MP1S","basis":"extension match mpeg","source":"","warning":""}]},{"filename":"C:\\users\\emc83\\temp\\39002087358793_D4\\AutoPlay\\Videos\\Pest Controllers.mpg","filesize": 0,"modified":"2006-01-10T12:25:43-05:00","errors": "empty source","matches": [{"ns":"wikidata","id":"Q28018471","format":"MPEG-2 program stream","URI":"http://www.wikidata.org/entity/Q28018471","mime":"video/MP2P","basis":"extension match mpg","source":"","warning":""},{"ns":"wikidata","id":"Q336284","format":"MPEG-1","URI":"http://www.wikidata.org/entity/Q336284","mime":"video/mpeg; audio/mpeg","basis":"extension match mpg","source":"","warning":""},{"ns":"wikidata","id":"Q28018470","format":"MPEG-1 program stream","URI":"http://www.wikidata.org/entity/Q28018470","mime":"video/MP1S","basis":"extension match mpg","source":"","warning":""}]},{"filename":"C:\\users\\emc83\\temp\\39002087358793_D4\\AutoPlay\\Videos\\Photographers.mpg","filesize": 0,"modified":"2006-01-11T00:12:45-05:00","errors": "empty source","matches": [{"ns":"wikidata","id":"Q28018471","format":"MPEG-2 program stream","URI":"http://www.wikidata.org/entity/Q28018471","mime":"video/MP2P","basis":"extension match mpg","source":"","warning":""},{"ns":"wikidata","id":"Q336284","format":"MPEG-1","URI":"http://www.wikidata.org/entity/Q336284","mime":"video/mpeg; audio/mpeg","basis":"extension match mpg","source":"","warning":""},{"ns":"wikidata","id":"Q28018470","format":"MPEG-1 program stream","URI":"http://www.wikidata.org/entity/Q28018470","mime":"video/MP1S","basis":"extension match mpg","source":"","warning":""}]},{"filename":"C:\\users\\emc83\\temp\\39002087358793_D4\\AutoPlay\\Videos\\Plasterers.mpg","filesize": 0,"modified":"2006-01-10T22:45:17-05:00","errors": "empty source","matches": [{"ns":"wikidata","id":"Q28018471","format":"MPEG-2 program stream","URI":"http://www.wikidata.org/entity/Q28018471","mime":"video/MP2P","basis":"extension match mpg","source":"","warning":""},{"ns":"wikidata","id":"Q336284","format":"MPEG-1","URI":"http://www.wikidata.org/entity/Q336284","mime":"video/mpeg; audio/mpeg","basis":"extension match mpg","source":"","warning":""},{"ns":"wikidata","id":"Q28018470","format":"MPEG-1 program stream","URI":"http://www.wikidata.org/entity/Q28018470","mime":"video/MP1S","basis":"extension match mpg","source":"","warning":""}]},{"filename":"C:\\users\\emc83\\temp\\39002087358793_D4\\AutoPlay\\Videos\\Plumbers.mpg","filesize": 0,"modified":"2006-01-10T22:45:50-05:00","errors": "empty source","matches": [{"ns":"wikidata","id":"Q28018471","format":"MPEG-2 program stream","URI":"http://www.wikidata.org/entity/Q28018471","mime":"video/MP2P","basis":"extension match mpg","source":"","warning":""},{"ns":"wikidata","id":"Q336284","format":"MPEG-1","URI":"http://www.wikidata.org/entity/Q336284","mime":"video/mpeg; audio/mpeg","basis":"extension match mpg","source":"","warning":""},{"ns":"wikidata","id":"Q28018470","format":"MPEG-1 program stream","URI":"http://www.wikidata.org/entity/Q28018470","mime":"video/MP1S","basis":"extension match mpg","source":"","warning":""}]},{"filename":"C:\\users\\emc83\\temp\\39002087358793_D4\\AutoPlay\\Videos\\Printing press operators.mpg","filesize": 0,"modified":"2006-01-11T00:13:48-05:00","errors": "empty source","matches": [{"ns":"wikidata","id":"Q28018471","format":"MPEG-2 program stream","URI":"http://www.wikidata.org/entity/Q28018471","mime":"video/MP2P","basis":"extension match mpg","source":"","warning":""},{"ns":"wikidata","id":"Q336284","format":"MPEG-1","URI":"http://www.wikidata.org/entity/Q336284","mime":"video/mpeg; audio/mpeg","basis":"extension match mpg","source":"","warning":""},{"ns":"wikidata","id":"Q28018470","format":"MPEG-1 program stream","URI":"http://www.wikidata.org/entity/Q28018470","mime":"video/MP1S","basis":"extension match mpg","source":"","warning":""}]},{"filename":"C:\\users\\emc83\\temp\\39002087358793_D4\\AutoPlay\\Videos\\Pruners.mpg","filesize": 0,"modified":"2006-01-10T12:26:06-05:00","errors": "empty source","matches": [{"ns":"wikidata","id":"Q28018471","format":"MPEG-2 program stream","URI":"http://www.wikidata.org/entity/Q28018471","mime":"video/MP2P","basis":"extension match mpg","source":"","warning":""},{"ns":"wikidata","id":"Q336284","format":"MPEG-1","URI":"http://www.wikidata.org/entity/Q336284","mime":"video/mpeg; audio/mpeg","basis":"extension match mpg","source":"","warning":""},{"ns":"wikidata","id":"Q28018470","format":"MPEG-1 program stream","URI":"http://www.wikidata.org/entity/Q28018470","mime":"video/MP1S","basis":"extension match mpg","source":"","warning":""}]},{"filename":"C:\\users\\emc83\\temp\\39002087358793_D4\\AutoPlay\\Videos\\Receptionists.mpg","filesize": 0,"modified":"2006-01-11T09:11:02-05:00","errors": "empty source","matches": [{"ns":"wikidata","id":"Q28018471","format":"MPEG-2 program stream","URI":"http://www.wikidata.org/entity/Q28018471","mime":"video/MP2P","basis":"extension match mpg","source":"","warning":""},{"ns":"wikidata","id":"Q336284","format":"MPEG-1","URI":"http://www.wikidata.org/entity/Q336284","mime":"video/mpeg; audio/mpeg","basis":"extension match mpg","source":"","warning":""},{"ns":"wikidata","id":"Q28018470","format":"MPEG-1 program stream","URI":"http://www.wikidata.org/entity/Q28018470","mime":"video/MP1S","basis":"extension match mpg","source":"","warning":""}]},{"filename":"C:\\users\\emc83\\temp\\39002087358793_D4\\AutoPlay\\Videos\\Recreation therapists.mpeg","filesize": 0,"modified":"2006-01-11T14:01:08-05:00","errors": "empty source","matches": [{"ns":"wikidata","id":"Q28018471","format":"MPEG-2 program stream","URI":"http://www.wikidata.org/entity/Q28018471","mime":"video/MP2P","basis":"extension match mpeg","source":"","warning":""},{"ns":"wikidata","id":"Q336284","format":"MPEG-1","URI":"http://www.wikidata.org/entity/Q336284","mime":"video/mpeg; audio/mpeg","basis":"extension match mpeg","source":"","warning":""},{"ns":"wikidata","id":"Q28018470","format":"MPEG-1 program stream","URI":"http://www.wikidata.org/entity/Q28018470","mime":"video/MP1S","basis":"extension match mpeg","source":"","warning":""}]},{"filename":"C:\\users\\emc83\\temp\\39002087358793_D4\\AutoPlay\\Videos\\Recreations workers.mpeg","filesize": 0,"modified":"2006-01-11T15:01:41-05:00","errors": "empty source","matches": [{"ns":"wikidata","id":"Q28018471","format":"MPEG-2 program stream","URI":"http://www.wikidata.org/entity/Q28018471","mime":"video/MP2P","basis":"extension match mpeg","source":"","warning":""},{"ns":"wikidata","id":"Q336284","format":"MPEG-1","URI":"http://www.wikidata.org/entity/Q336284","mime":"video/mpeg; audio/mpeg","basis":"extension match mpeg","source":"","warning":""},{"ns":"wikidata","id":"Q28018470","format":"MPEG-1 program stream","URI":"http://www.wikidata.org/entity/Q28018470","mime":"video/MP1S","basis":"extension match mpeg","source":"","warning":""}]},{"filename":"C:\\users\\emc83\\temp\\39002087358793_D4\\AutoPlay\\Videos\\Refuse.mpeg","filesize": 0,"modified":"2006-01-11T21:56:19-05:00","errors": "empty source","matches": [{"ns":"wikidata","id":"Q28018471","format":"MPEG-2 program stream","URI":"http://www.wikidata.org/entity/Q28018471","mime":"video/MP2P","basis":"extension match mpeg","source":"","warning":""},{"ns":"wikidata","id":"Q336284","format":"MPEG-1","URI":"http://www.wikidata.org/entity/Q336284","mime":"video/mpeg; audio/mpeg","basis":"extension match mpeg","source":"","warning":""},{"ns":"wikidata","id":"Q28018470","format":"MPEG-1 program stream","URI":"http://www.wikidata.org/entity/Q28018470","mime":"video/MP1S","basis":"extension match mpeg","source":"","warning":""}]},{"filename":"C:\\users\\emc83\\temp\\39002087358793_D4\\AutoPlay\\Videos\\Rehabilitation counselors.mpeg","filesize": 0,"modified":"2006-01-11T16:34:42-05:00","errors": "empty source","matches": [{"ns":"wikidata","id":"Q28018471","format":"MPEG-2 program stream","URI":"http://www.wikidata.org/entity/Q28018471","mime":"video/MP2P","basis":"extension match mpeg","source":"","warning":""},{"ns":"wikidata","id":"Q336284","format":"MPEG-1","URI":"http://www.wikidata.org/entity/Q336284","mime":"video/mpeg; audio/mpeg","basis":"extension match mpeg","source":"","warning":""},{"ns":"wikidata","id":"Q28018470","format":"MPEG-1 program stream","URI":"http://www.wikidata.org/entity/Q28018470","mime":"video/MP1S","basis":"extension match mpeg","source":"","warning":""}]},{"filename":"C:\\users\\emc83\\temp\\39002087358793_D4\\AutoPlay\\Videos\\Roofers.mpg","filesize": 0,"modified":"2006-01-10T22:46:25-05:00","errors": "empty source","matches": [{"ns":"wikidata","id":"Q28018471","format":"MPEG-2 program stream","URI":"http://www.wikidata.org/entity/Q28018471","mime":"video/MP2P","basis":"extension match mpg","source":"","warning":""},{"ns":"wikidata","id":"Q336284","format":"MPEG-1","URI":"http://www.wikidata.org/entity/Q336284","mime":"video/mpeg; audio/mpeg","basis":"extension match mpg","source":"","warning":""},{"ns":"wikidata","id":"Q28018470","format":"MPEG-1 program stream","URI":"http://www.wikidata.org/entity/Q28018470","mime":"video/MP1S","basis":"extension match mpg","source":"","warning":""}]},{"filename":"C:\\users\\emc83\\temp\\39002087358793_D4\\AutoPlay\\Videos\\Salesperson.mpeg","filesize": 0,"modified":"2006-01-11T21:23:00-05:00","errors": "empty source","matches": [{"ns":"wikidata","id":"Q28018471","format":"MPEG-2 program stream","URI":"http://www.wikidata.org/entity/Q28018471","mime":"video/MP2P","basis":"extension match mpeg","source":"","warning":""},{"ns":"wikidata","id":"Q336284","format":"MPEG-1","URI":"http://www.wikidata.org/entity/Q336284","mime":"video/mpeg; audio/mpeg","basis":"extension match mpeg","source":"","warning":""},{"ns":"wikidata","id":"Q28018470","format":"MPEG-1 program stream","URI":"http://www.wikidata.org/entity/Q28018470","mime":"video/MP1S","basis":"extension match mpeg","source":"","warning":""}]},{"filename":"C:\\users\\emc83\\temp\\39002087358793_D4\\AutoPlay\\Videos\\Secretaries.mpg","filesize": 0,"modified":"2006-01-11T09:11:48-05:00","errors": "empty source","matches": [{"ns":"wikidata","id":"Q28018471","format":"MPEG-2 program stream","URI":"http://www.wikidata.org/entity/Q28018471","mime":"video/MP2P","basis":"extension match mpg","source":"","warning":""},{"ns":"wikidata","id":"Q336284","format":"MPEG-1","URI":"http://www.wikidata.org/entity/Q336284","mime":"video/mpeg; audio/mpeg","basis":"extension match mpg","source":"","warning":""},{"ns":"wikidata","id":"Q28018470","format":"MPEG-1 program stream","URI":"http://www.wikidata.org/entity/Q28018470","mime":"video/MP1S","basis":"extension match mpg","source":"","warning":""}]},{"filename":"C:\\users\\emc83\\temp\\39002087358793_D4\\AutoPlay\\Videos\\Service station.mpeg","filesize": 0,"modified":"2006-01-11T21:23:10-05:00","errors": "empty source","matches": [{"ns":"wikidata","id":"Q28018471","format":"MPEG-2 program stream","URI":"http://www.wikidata.org/entity/Q28018471","mime":"video/MP2P","basis":"extension match mpeg","source":"","warning":""},{"ns":"wikidata","id":"Q336284","format":"MPEG-1","URI":"http://www.wikidata.org/entity/Q336284","mime":"video/mpeg; audio/mpeg","basis":"extension match mpeg","source":"","warning":""},{"ns":"wikidata","id":"Q28018470","format":"MPEG-1 program stream","URI":"http://www.wikidata.org/entity/Q28018470","mime":"video/MP1S","basis":"extension match mpeg","source":"","warning":""}]},{"filename":"C:\\users\\emc83\\temp\\39002087358793_D4\\AutoPlay\\Videos\\Sewing machine operators.mpeg","filesize": 0,"modified":"2006-01-11T20:52:06-05:00","errors": "empty source","matches": [{"ns":"wikidata","id":"Q28018471","format":"MPEG-2 program stream","URI":"http://www.wikidata.org/entity/Q28018471","mime":"video/MP2P","basis":"extension match mpeg","source":"","warning":""},{"ns":"wikidata","id":"Q336284","format":"MPEG-1","URI":"http://www.wikidata.org/entity/Q336284","mime":"video/mpeg; audio/mpeg","basis":"extension match mpeg","source":"","warning":""},{"ns":"wikidata","id":"Q28018470","format":"MPEG-1 program stream","URI":"http://www.wikidata.org/entity/Q28018470","mime":"video/MP1S","basis":"extension match mpeg","source":"","warning":""}]},{"filename":"C:\\users\\emc83\\temp\\39002087358793_D4\\AutoPlay\\Videos\\Shampooers.mpeg","filesize": 0,"modified":"2006-01-11T21:23:28-05:00","errors": "empty source","matches": [{"ns":"wikidata","id":"Q28018471","format":"MPEG-2 program stream","URI":"http://www.wikidata.org/entity/Q28018471","mime":"video/MP2P","basis":"extension match mpeg","source":"","warning":""},{"ns":"wikidata","id":"Q336284","format":"MPEG-1","URI":"http://www.wikidata.org/entity/Q336284","mime":"video/mpeg; audio/mpeg","basis":"extension match mpeg","source":"","warning":""},{"ns":"wikidata","id":"Q28018470","format":"MPEG-1 program stream","URI":"http://www.wikidata.org/entity/Q28018470","mime":"video/MP1S","basis":"extension match mpeg","source":"","warning":""}]},{"filename":"C:\\users\\emc83\\temp\\39002087358793_D4\\AutoPlay\\Videos\\Sheet metal workers.mpg","filesize": 0,"modified":"2006-01-10T22:47:03-05:00","errors": "empty source","matches": [{"ns":"wikidata","id":"Q28018471","format":"MPEG-2 program stream","URI":"http://www.wikidata.org/entity/Q28018471","mime":"video/MP2P","basis":"extension match mpg","source":"","warning":""},{"ns":"wikidata","id":"Q336284","format":"MPEG-1","URI":"http://www.wikidata.org/entity/Q336284","mime":"video/mpeg; audio/mpeg","basis":"extension match mpg","source":"","warning":""},{"ns":"wikidata","id":"Q28018470","format":"MPEG-1 program stream","URI":"http://www.wikidata.org/entity/Q28018470","mime":"video/MP1S","basis":"extension match mpg","source":"","warning":""}]},{"filename":"C:\\users\\emc83\\temp\\39002087358793_D4\\AutoPlay\\Videos\\Shipping.mpeg","filesize": 0,"modified":"2006-01-11T21:23:42-05:00","errors": "empty source","matches": [{"ns":"wikidata","id":"Q28018471","format":"MPEG-2 program stream","URI":"http://www.wikidata.org/entity/Q28018471","mime":"video/MP2P","basis":"extension match mpeg","source":"","warning":""},{"ns":"wikidata","id":"Q336284","format":"MPEG-1","URI":"http://www.wikidata.org/entity/Q336284","mime":"video/mpeg; audio/mpeg","basis":"extension match mpeg","source":"","warning":""},{"ns":"wikidata","id":"Q28018470","format":"MPEG-1 program stream","URI":"http://www.wikidata.org/entity/Q28018470","mime":"video/MP1S","basis":"extension match mpeg","source":"","warning":""}]},{"filename":"C:\\users\\emc83\\temp\\39002087358793_D4\\AutoPlay\\Videos\\Sign language interpreter.mpg","filesize": 0,"modified":"2006-01-11T00:14:28-05:00","errors": "empty source","matches": [{"ns":"wikidata","id":"Q28018471","format":"MPEG-2 program stream","URI":"http://www.wikidata.org/entity/Q28018471","mime":"video/MP2P","basis":"extension match mpg","source":"","warning":""},{"ns":"wikidata","id":"Q336284","format":"MPEG-1","URI":"http://www.wikidata.org/entity/Q336284","mime":"video/mpeg; audio/mpeg","basis":"extension match mpg","source":"","warning":""},{"ns":"wikidata","id":"Q28018470","format":"MPEG-1 program stream","URI":"http://www.wikidata.org/entity/Q28018470","mime":"video/MP1S","basis":"extension match mpg","source":"","warning":""}]},{"filename":"C:\\users\\emc83\\temp\\39002087358793_D4\\AutoPlay\\Videos\\Social and Human Services Assistants.mpeg","filesize": 0,"modified":"2006-01-11T16:35:07-05:00","errors": "empty source","matches": [{"ns":"wikidata","id":"Q28018471","format":"MPEG-2 program stream","URI":"http://www.wikidata.org/entity/Q28018471","mime":"video/MP2P","basis":"extension match mpeg","source":"","warning":""},{"ns":"wikidata","id":"Q336284","format":"MPEG-1","URI":"http://www.wikidata.org/entity/Q336284","mime":"video/mpeg; audio/mpeg","basis":"extension match mpeg","source":"","warning":""},{"ns":"wikidata","id":"Q28018470","format":"MPEG-1 program stream","URI":"http://www.wikidata.org/entity/Q28018470","mime":"video/MP1S","basis":"extension match mpeg","source":"","warning":""}]},{"filename":"C:\\users\\emc83\\temp\\39002087358793_D4\\AutoPlay\\Videos\\Structural Iron and Steel workers.mpg","filesize": 0,"modified":"2006-01-10T22:48:20-05:00","errors": "empty source","matches": [{"ns":"wikidata","id":"Q28018471","format":"MPEG-2 program stream","URI":"http://www.wikidata.org/entity/Q28018471","mime":"video/MP2P","basis":"extension match mpg","source":"","warning":""},{"ns":"wikidata","id":"Q336284","format":"MPEG-1","URI":"http://www.wikidata.org/entity/Q336284","mime":"video/mpeg; audio/mpeg","basis":"extension match mpg","source":"","warning":""},{"ns":"wikidata","id":"Q28018470","format":"MPEG-1 program stream","URI":"http://www.wikidata.org/entity/Q28018470","mime":"video/MP1S","basis":"extension match mpg","source":"","warning":""}]},{"filename":"C:\\users\\emc83\\temp\\39002087358793_D4\\AutoPlay\\Videos\\Tax preparers.mpeg","filesize": 0,"modified":"2006-01-11T10:49:21-05:00","errors": "empty source","matches": [{"ns":"wikidata","id":"Q28018471","format":"MPEG-2 program stream","URI":"http://www.wikidata.org/entity/Q28018471","mime":"video/MP2P","basis":"extension match mpeg","source":"","warning":""},{"ns":"wikidata","id":"Q336284","format":"MPEG-1","URI":"http://www.wikidata.org/entity/Q336284","mime":"video/mpeg; audio/mpeg","basis":"extension match mpeg","source":"","warning":""},{"ns":"wikidata","id":"Q28018470","format":"MPEG-1 program stream","URI":"http://www.wikidata.org/entity/Q28018470","mime":"video/MP1S","basis":"extension match mpeg","source":"","warning":""}]},{"filename":"C:\\users\\emc83\\temp\\39002087358793_D4\\AutoPlay\\Videos\\Taxi drivers.mpeg","filesize": 0,"modified":"2006-01-11T21:56:38-05:00","errors": "empty source","matches": [{"ns":"wikidata","id":"Q28018471","format":"MPEG-2 program stream","URI":"http://www.wikidata.org/entity/Q28018471","mime":"video/MP2P","basis":"extension match mpeg","source":"","warning":""},{"ns":"wikidata","id":"Q336284","format":"MPEG-1","URI":"http://www.wikidata.org/entity/Q336284","mime":"video/mpeg; audio/mpeg","basis":"extension match mpeg","source":"","warning":""},{"ns":"wikidata","id":"Q28018470","format":"MPEG-1 program stream","URI":"http://www.wikidata.org/entity/Q28018470","mime":"video/MP1S","basis":"extension match mpeg","source":"","warning":""}]},{"filename":"C:\\users\\emc83\\temp\\39002087358793_D4\\AutoPlay\\Videos\\Teaching assistants.mpeg","filesize": 0,"modified":"2006-01-11T10:24:44-05:00","errors": "empty source","matches": [{"ns":"wikidata","id":"Q28018471","format":"MPEG-2 program stream","URI":"http://www.wikidata.org/entity/Q28018471","mime":"video/MP2P","basis":"extension match mpeg","source":"","warning":""},{"ns":"wikidata","id":"Q336284","format":"MPEG-1","URI":"http://www.wikidata.org/entity/Q336284","mime":"video/mpeg; audio/mpeg","basis":"extension match mpeg","source":"","warning":""},{"ns":"wikidata","id":"Q28018470","format":"MPEG-1 program stream","URI":"http://www.wikidata.org/entity/Q28018470","mime":"video/MP1S","basis":"extension match mpeg","source":"","warning":""}]},{"filename":"C:\\users\\emc83\\temp\\39002087358793_D4\\AutoPlay\\Videos\\Telecommunication line installer.mpg","filesize": 0,"modified":"2006-01-11T00:15:25-05:00","errors": "empty source","matches": [{"ns":"wikidata","id":"Q28018471","format":"MPEG-2 program stream","URI":"http://www.wikidata.org/entity/Q28018471","mime":"video/MP2P","basis":"extension match mpg","source":"","warning":""},{"ns":"wikidata","id":"Q336284","format":"MPEG-1","URI":"http://www.wikidata.org/entity/Q336284","mime":"video/mpeg; audio/mpeg","basis":"extension match mpg","source":"","warning":""},{"ns":"wikidata","id":"Q28018470","format":"MPEG-1 program stream","URI":"http://www.wikidata.org/entity/Q28018470","mime":"video/MP1S","basis":"extension match mpg","source":"","warning":""}]},{"filename":"C:\\users\\emc83\\temp\\39002087358793_D4\\AutoPlay\\Videos\\Telemarketers.mpeg","filesize": 0,"modified":"2006-01-11T21:24:01-05:00","errors": "empty source","matches": [{"ns":"wikidata","id":"Q28018471","format":"MPEG-2 program stream","URI":"http://www.wikidata.org/entity/Q28018471","mime":"video/MP2P","basis":"extension match mpeg","source":"","warning":""},{"ns":"wikidata","id":"Q336284","format":"MPEG-1","URI":"http://www.wikidata.org/entity/Q336284","mime":"video/mpeg; audio/mpeg","basis":"extension match mpeg","source":"","warning":""},{"ns":"wikidata","id":"Q28018470","format":"MPEG-1 program stream","URI":"http://www.wikidata.org/entity/Q28018470","mime":"video/MP1S","basis":"extension match mpeg","source":"","warning":""}]},{"filename":"C:\\users\\emc83\\temp\\39002087358793_D4\\AutoPlay\\Videos\\Tire repairers.mpeg","filesize": 0,"modified":"2006-01-11T21:56:52-05:00","errors": "empty source","matches": [{"ns":"wikidata","id":"Q28018471","format":"MPEG-2 program stream","URI":"http://www.wikidata.org/entity/Q28018471","mime":"video/MP2P","basis":"extension match mpeg","source":"","warning":""},{"ns":"wikidata","id":"Q336284","format":"MPEG-1","URI":"http://www.wikidata.org/entity/Q336284","mime":"video/mpeg; audio/mpeg","basis":"extension match mpeg","source":"","warning":""},{"ns":"wikidata","id":"Q28018470","format":"MPEG-1 program stream","URI":"http://www.wikidata.org/entity/Q28018470","mime":"video/MP1S","basis":"extension match mpeg","source":"","warning":""}]},{"filename":"C:\\users\\emc83\\temp\\39002087358793_D4\\AutoPlay\\Videos\\Tour guides.mpeg","filesize": 0,"modified":"2006-01-11T15:01:59-05:00","errors": "empty source","matches": [{"ns":"wikidata","id":"Q28018471","format":"MPEG-2 program stream","URI":"http://www.wikidata.org/entity/Q28018471","mime":"video/MP2P","basis":"extension match mpeg","source":"","warning":""},{"ns":"wikidata","id":"Q336284","format":"MPEG-1","URI":"http://www.wikidata.org/entity/Q336284","mime":"video/mpeg; audio/mpeg","basis":"extension match mpeg","source":"","warning":""},{"ns":"wikidata","id":"Q28018470","format":"MPEG-1 program stream","URI":"http://www.wikidata.org/entity/Q28018470","mime":"video/MP1S","basis":"extension match mpeg","source":"","warning":""}]},{"filename":"C:\\users\\emc83\\temp\\39002087358793_D4\\AutoPlay\\Videos\\Training and development.mpeg","filesize": 0,"modified":"2006-01-11T10:25:11-05:00","errors": "empty source","matches": [{"ns":"wikidata","id":"Q28018471","format":"MPEG-2 program stream","URI":"http://www.wikidata.org/entity/Q28018471","mime":"video/MP2P","basis":"extension match mpeg","source":"","warning":""},{"ns":"wikidata","id":"Q336284","format":"MPEG-1","URI":"http://www.wikidata.org/entity/Q336284","mime":"video/mpeg; audio/mpeg","basis":"extension match mpeg","source":"","warning":""},{"ns":"wikidata","id":"Q28018470","format":"MPEG-1 program stream","URI":"http://www.wikidata.org/entity/Q28018470","mime":"video/MP1S","basis":"extension match mpeg","source":"","warning":""}]},{"filename":"C:\\users\\emc83\\temp\\39002087358793_D4\\AutoPlay\\Videos\\Transportation Distribution.mpeg","filesize": 0,"modified":"2006-01-11T21:52:51-05:00","errors": "empty source","matches": [{"ns":"wikidata","id":"Q28018471","format":"MPEG-2 program stream","URI":"http://www.wikidata.org/entity/Q28018471","mime":"video/MP2P","basis":"extension match mpeg","source":"","warning":""},{"ns":"wikidata","id":"Q336284","format":"MPEG-1","URI":"http://www.wikidata.org/entity/Q336284","mime":"video/mpeg; audio/mpeg","basis":"extension match mpeg","source":"","warning":""},{"ns":"wikidata","id":"Q28018470","format":"MPEG-1 program stream","URI":"http://www.wikidata.org/entity/Q28018470","mime":"video/MP1S","basis":"extension match mpeg","source":"","warning":""}]},{"filename":"C:\\users\\emc83\\temp\\39002087358793_D4\\AutoPlay\\Videos\\Truck drivers heavy.mpeg","filesize": 0,"modified":"2006-01-11T21:57:00-05:00","errors": "empty source","matches": [{"ns":"wikidata","id":"Q28018471","format":"MPEG-2 program stream","URI":"http://www.wikidata.org/entity/Q28018471","mime":"video/MP2P","basis":"extension match mpeg","source":"","warning":""},{"ns":"wikidata","id":"Q336284","format":"MPEG-1","URI":"http://www.wikidata.org/entity/Q336284","mime":"video/mpeg; audio/mpeg","basis":"extension match mpeg","source":"","warning":""},{"ns":"wikidata","id":"Q28018470","format":"MPEG-1 program stream","URI":"http://www.wikidata.org/entity/Q28018470","mime":"video/MP1S","basis":"extension match mpeg","source":"","warning":""}]},{"filename":"C:\\users\\emc83\\temp\\39002087358793_D4\\AutoPlay\\Videos\\Truck drivers light.mpeg","filesize": 0,"modified":"2006-01-11T21:57:19-05:00","errors": "empty source","matches": [{"ns":"wikidata","id":"Q28018471","format":"MPEG-2 program stream","URI":"http://www.wikidata.org/entity/Q28018471","mime":"video/MP2P","basis":"extension match mpeg","source":"","warning":""},{"ns":"wikidata","id":"Q336284","format":"MPEG-1","URI":"http://www.wikidata.org/entity/Q336284","mime":"video/mpeg; audio/mpeg","basis":"extension match mpeg","source":"","warning":""},{"ns":"wikidata","id":"Q28018470","format":"MPEG-1 program stream","URI":"http://www.wikidata.org/entity/Q28018470","mime":"video/MP1S","basis":"extension match mpeg","source":"","warning":""}]},{"filename":"C:\\users\\emc83\\temp\\39002087358793_D4\\AutoPlay\\Videos\\Two year degree.mpeg","filesize": 0,"modified":"2006-01-11T22:46:57-05:00","errors": "empty source","matches": [{"ns":"wikidata","id":"Q28018471","format":"MPEG-2 program stream","URI":"http://www.wikidata.org/entity/Q28018471","mime":"video/MP2P","basis":"extension match mpeg","source":"","warning":""},{"ns":"wikidata","id":"Q336284","format":"MPEG-1","URI":"http://www.wikidata.org/entity/Q336284","mime":"video/mpeg; audio/mpeg","basis":"extension match mpeg","source":"","warning":""},{"ns":"wikidata","id":"Q28018470","format":"MPEG-1 program stream","URI":"http://www.wikidata.org/entity/Q28018470","mime":"video/MP1S","basis":"extension match mpeg","source":"","warning":""}]},{"filename":"C:\\users\\emc83\\temp\\39002087358793_D4\\AutoPlay\\Videos\\Upholsterers.mpeg","filesize": 0,"modified":"2006-01-11T21:24:20-05:00","errors": "empty source","matches": [{"ns":"wikidata","id":"Q28018471","format":"MPEG-2 program stream","URI":"http://www.wikidata.org/entity/Q28018471","mime":"video/MP2P","basis":"extension match mpeg","source":"","warning":""},{"ns":"wikidata","id":"Q336284","format":"MPEG-1","URI":"http://www.wikidata.org/entity/Q336284","mime":"video/mpeg; audio/mpeg","basis":"extension match mpeg","source":"","warning":""},{"ns":"wikidata","id":"Q28018470","format":"MPEG-1 program stream","URI":"http://www.wikidata.org/entity/Q28018470","mime":"video/MP1S","basis":"extension match mpeg","source":"","warning":""}]},{"filename":"C:\\users\\emc83\\temp\\39002087358793_D4\\AutoPlay\\Videos\\Veterinary Assistants.mpg","filesize": 0,"modified":"2006-01-10T12:26:48-05:00","errors": "empty source","matches": [{"ns":"wikidata","id":"Q28018471","format":"MPEG-2 program stream","URI":"http://www.wikidata.org/entity/Q28018471","mime":"video/MP2P","basis":"extension match mpg","source":"","warning":""},{"ns":"wikidata","id":"Q336284","format":"MPEG-1","URI":"http://www.wikidata.org/entity/Q336284","mime":"video/mpeg; audio/mpeg","basis":"extension match mpg","source":"","warning":""},{"ns":"wikidata","id":"Q28018470","format":"MPEG-1 program stream","URI":"http://www.wikidata.org/entity/Q28018470","mime":"video/MP1S","basis":"extension match mpg","source":"","warning":""}]},{"filename":"C:\\users\\emc83\\temp\\39002087358793_D4\\AutoPlay\\Videos\\Waiters.mpeg","filesize": 0,"modified":"2006-01-11T15:02:11-05:00","errors": "empty source","matches": [{"ns":"wikidata","id":"Q28018471","format":"MPEG-2 program stream","URI":"http://www.wikidata.org/entity/Q28018471","mime":"video/MP2P","basis":"extension match mpeg","source":"","warning":""},{"ns":"wikidata","id":"Q336284","format":"MPEG-1","URI":"http://www.wikidata.org/entity/Q336284","mime":"video/mpeg; audio/mpeg","basis":"extension match mpeg","source":"","warning":""},{"ns":"wikidata","id":"Q28018470","format":"MPEG-1 program stream","URI":"http://www.wikidata.org/entity/Q28018470","mime":"video/MP1S","basis":"extension match mpeg","source":"","warning":""}]},{"filename":"C:\\users\\emc83\\temp\\39002087358793_D4\\AutoPlay\\Videos\\Water and liquid.mpeg","filesize": 0,"modified":"2006-01-11T11:50:26-05:00","errors": "empty source","matches": [{"ns":"wikidata","id":"Q28018471","format":"MPEG-2 program stream","URI":"http://www.wikidata.org/entity/Q28018471","mime":"video/MP2P","basis":"extension match mpeg","source":"","warning":""},{"ns":"wikidata","id":"Q336284","format":"MPEG-1","URI":"http://www.wikidata.org/entity/Q336284","mime":"video/mpeg; audio/mpeg","basis":"extension match mpeg","source":"","warning":""},{"ns":"wikidata","id":"Q28018470","format":"MPEG-1 program stream","URI":"http://www.wikidata.org/entity/Q28018470","mime":"video/MP1S","basis":"extension match mpeg","source":"","warning":""}]},{"filename":"C:\\users\\emc83\\temp\\39002087358793_D4\\AutoPlay\\Videos\\Webmasters.mpeg","filesize": 0,"modified":"2006-01-11T17:01:34-05:00","errors": "empty source","matches": [{"ns":"wikidata","id":"Q28018471","format":"MPEG-2 program stream","URI":"http://www.wikidata.org/entity/Q28018471","mime":"video/MP2P","basis":"extension match mpeg","source":"","warning":""},{"ns":"wikidata","id":"Q336284","format":"MPEG-1","URI":"http://www.wikidata.org/entity/Q336284","mime":"video/mpeg; audio/mpeg","basis":"extension match mpeg","source":"","warning":""},{"ns":"wikidata","id":"Q28018470","format":"MPEG-1 program stream","URI":"http://www.wikidata.org/entity/Q28018470","mime":"video/MP1S","basis":"extension match mpeg","source":"","warning":""}]},{"filename":"C:\\users\\emc83\\temp\\39002087358793_D4\\AutoPlay\\Videos\\Welders.mpeg","filesize": 0,"modified":"2006-01-11T20:52:19-05:00","errors": "empty source","matches": [{"ns":"wikidata","id":"Q28018471","format":"MPEG-2 program stream","URI":"http://www.wikidata.org/entity/Q28018471","mime":"video/MP2P","basis":"extension match mpeg","source":"","warning":""},{"ns":"wikidata","id":"Q336284","format":"MPEG-1","URI":"http://www.wikidata.org/entity/Q336284","mime":"video/mpeg; audio/mpeg","basis":"extension match mpeg","source":"","warning":""},{"ns":"wikidata","id":"Q28018470","format":"MPEG-1 program stream","URI":"http://www.wikidata.org/entity/Q28018470","mime":"video/MP1S","basis":"extension match mpeg","source":"","warning":""}]},{"filename":"C:\\users\\emc83\\temp\\39002087358793_D4\\AutoPlay\\Videos\\Woodworking machine operators.mpeg","filesize": 0,"modified":"2006-01-11T20:52:41-05:00","errors": "empty source","matches": [{"ns":"wikidata","id":"Q28018471","format":"MPEG-2 program stream","URI":"http://www.wikidata.org/entity/Q28018471","mime":"video/MP2P","basis":"extension match mpeg","source":"","warning":""},{"ns":"wikidata","id":"Q336284","format":"MPEG-1","URI":"http://www.wikidata.org/entity/Q336284","mime":"video/mpeg; audio/mpeg","basis":"extension match mpeg","source":"","warning":""},{"ns":"wikidata","id":"Q28018470","format":"MPEG-1 program stream","URI":"http://www.wikidata.org/entity/Q28018470","mime":"video/MP1S","basis":"extension match mpeg","source":"","warning":""}]},{"filename":"C:\\users\\emc83\\temp\\39002087358793_D4\\AutoPlay\\Videos\\Working outside.mpeg","filesize": 0,"modified":"2006-01-11T22:47:53-05:00","errors": "empty source","matches": [{"ns":"wikidata","id":"Q28018471","format":"MPEG-2 program stream","URI":"http://www.wikidata.org/entity/Q28018471","mime":"video/MP2P","basis":"extension match mpeg","source":"","warning":""},{"ns":"wikidata","id":"Q336284","format":"MPEG-1","URI":"http://www.wikidata.org/entity/Q336284","mime":"video/mpeg; audio/mpeg","basis":"extension match mpeg","source":"","warning":""},{"ns":"wikidata","id":"Q28018470","format":"MPEG-1 program stream","URI":"http://www.wikidata.org/entity/Q28018470","mime":"video/MP1S","basis":"extension match mpeg","source":"","warning":""}]},{"filename":"C:\\users\\emc83\\temp\\39002087358793_D4\\AutoPlay\\Videos\\Writer.mpg","filesize": 0,"modified":"2006-01-11T00:16:35-05:00","errors": "empty source","matches": [{"ns":"wikidata","id":"Q28018471","format":"MPEG-2 program stream","URI":"http://www.wikidata.org/entity/Q28018471","mime":"video/MP2P","basis":"extension match mpg","source":"","warning":""},{"ns":"wikidata","id":"Q336284","format":"MPEG-1","URI":"http://www.wikidata.org/entity/Q336284","mime":"video/mpeg; audio/mpeg","basis":"extension match mpg","source":"","warning":""},{"ns":"wikidata","id":"Q28018470","format":"MPEG-1 program stream","URI":"http://www.wikidata.org/entity/Q28018470","mime":"video/MP1S","basis":"extension match mpg","source":"","warning":""}]},{"filename":"C:\\users\\emc83\\temp\\39002087358793_D4\\AutoPlay\\Videos\\manufaturing.mpeg","filesize": 24432488,"modified":"2006-01-11T20:48:07-05:00","errors": "","matches": [{"ns":"wikidata","id":"Q28018471","format":"MPEG-2 program stream","URI":"http://www.wikidata.org/entity/Q28018471","mime":"video/MP2P","basis":"extension match mpeg","source":"","warning":""},{"ns":"wikidata","id":"Q336284","format":"MPEG-1","URI":"http://www.wikidata.org/entity/Q336284","mime":"video/mpeg; audio/mpeg","basis":"extension match mpeg","source":"","warning":""},{"ns":"wikidata","id":"Q28018470","format":"MPEG-1 program stream","URI":"http://www.wikidata.org/entity/Q28018470","mime":"video/MP1S","basis":"extension match mpeg","source":"","warning":""}]},{"filename":"C:\\users\\emc83\\temp\\39002087358793_D4\\AutoPlay\\autorun.cdd","filesize": 222842,"modified":"2006-02-13T10:51:27-05:00","errors": "","matches": [{"ns":"wikidata","id":"UNKNOWN","format":"","URI":"","mime":"","basis":"","source":"","warning":"no match"}]},{"filename":"C:\\users\\emc83\\temp\\39002087358793_D4\\Thumbs.db","filesize": 0,"modified":"2005-11-11T22:18:07-05:00","errors": "empty source","matches": [{"ns":"wikidata","id":"Q51035227","format":"Paradox Database Table, version 4","URI":"http://www.wikidata.org/entity/Q51035227","mime":"","basis":"extension match db","source":"","warning":""},{"ns":"wikidata","id":"Q28600435","format":"Consolidated.db","URI":"http://www.wikidata.org/entity/Q28600435","mime":"","basis":"extension match db","source":"","warning":""},{"ns":"wikidata","id":"Q930281","format":"Windows thumbnail cache","URI":"http://www.wikidata.org/entity/Q930281","mime":"","basis":"extension match db","source":"","warning":""},{"ns":"wikidata","id":"Q51837224","format":"Paradox Database Table, version 7","URI":"http://www.wikidata.org/entity/Q51837224","mime":"","basis":"extension match db","source":"","warning":""},{"ns":"wikidata","id":"Q28600453","format":"SQLite database file format","URI":"http://www.wikidata.org/entity/Q28600453","mime":"application/vnd.sqlite3","basis":"extension match db","source":"","warning":""},{"ns":"wikidata","id":"Q28600454","format":"DB (Watcom-SQL)","URI":"http://www.wikidata.org/entity/Q28600454","mime":"","basis":"extension match db","source":"","warning":""},{"ns":"wikidata","id":"Q51034969","format":"Paradox Database Table format, version 3","URI":"http://www.wikidata.org/entity/Q51034969","mime":"","basis":"extension match db","source":"","warning":""},{"ns":"wikidata","id":"Q51035340","format":"Paradox Database Table, version 5","URI":"http://www.wikidata.org/entity/Q51035340","mime":"","basis":"extension match db","source":"","warning":""}]},{"filename":"C:\\users\\emc83\\temp\\39002087358793_D4\\autorun.exe","filesize": 0,"modified":"2006-02-13T10:51:27-05:00","errors": "empty source","matches": [{"ns":"wikidata","id":"Q28777715","format":"NSIS","URI":"http://www.wikidata.org/entity/Q28777715","mime":"","basis":"extension match exe","source":"","warning":""},{"ns":"wikidata","id":"Q66244789","format":"ScreenCam stand-alone Movies format","URI":"http://www.wikidata.org/entity/Q66244789","mime":"","basis":"extension match exe","source":"","warning":""},{"ns":"wikidata","id":"Q28758002","format":"Inno Setup self-extracting archive","URI":"http://www.wikidata.org/entity/Q28758002","mime":"","basis":"extension match exe","source":"","warning":""},{"ns":"wikidata","id":"Q623334","format":".exe","URI":"http://www.wikidata.org/entity/Q623334","mime":"","basis":"extension match exe","source":"","warning":""},{"ns":"wikidata","id":"Q4042979","format":"Linear Executable","URI":"http://www.wikidata.org/entity/Q4042979","mime":"","basis":"extension match exe","source":"","warning":""},{"ns":"wikidata","id":"Q1343830","format":"Executable and Linkable Format","URI":"http://www.wikidata.org/entity/Q1343830","mime":"","basis":"extension match exe","source":"","warning":""},{"ns":"wikidata","id":"Q47455565","format":"Windows Portable Executable file format, 64-bit","URI":"http://www.wikidata.org/entity/Q47455565","mime":"application/vnd.microsoft.portable-executable","basis":"extension match exe","source":"","warning":""},{"ns":"wikidata","id":"Q1882110","format":"DOS MZ executable","URI":"http://www.wikidata.org/entity/Q1882110","mime":"application/x-msdos-program; application/x-dosexec","basis":"extension match exe","source":"","warning":""},{"ns":"wikidata","id":"Q47455466","format":"Windows Portable Executable file format, 32-bit","URI":"http://www.wikidata.org/entity/Q47455466","mime":"application/vnd.microsoft.portable-executable","basis":"extension match exe","source":"","warning":""},{"ns":"wikidata","id":"Q1076355","format":"Portable Executable","URI":"http://www.wikidata.org/entity/Q1076355","mime":"application/efi; application/vnd.microsoft.portable-executable","basis":"extension match exe","source":"","warning":""},{"ns":"wikidata","id":"Q4045294","format":"New Executable","URI":"http://www.wikidata.org/entity/Q4045294","mime":"","basis":"extension match exe","source":"","warning":""}]},{"filename":"C:\\users\\emc83\\temp\\39002087358793_D4\\autorun.inf","filesize": 0,"modified":"2006-02-13T10:51:27-05:00","errors": "empty source","matches": [{"ns":"wikidata","id":"Q16996920","format":"Windows Setup Information File","URI":"http://www.wikidata.org/entity/Q16996920","mime":"application/inf","basis":"extension match inf","source":"","warning":""},{"ns":"wikidata","id":"Q66811836","format":"Inform source code file","URI":"http://www.wikidata.org/entity/Q66811836","mime":"","basis":"extension match inf","source":"","warning":""},{"ns":"wikidata","id":"Q28600763","format":"Electronic Arts INF","URI":"http://www.wikidata.org/entity/Q28600763","mime":"","basis":"extension match inf","source":"","warning":""},{"ns":"wikidata","id":"Q1662484","format":"Information Presentation Facility","URI":"http://www.wikidata.org/entity/Q1662484","mime":"","basis":"extension match inf","source":"","warning":""},{"ns":"wikidata","id":"Q684554","format":"Autorun.inf","URI":"http://www.wikidata.org/entity/Q684554","mime":"application/x-inf","basis":"extension match inf","source":"","warning":""}]},{"filename":"C:\\users\\emc83\\temp\\39002087358793_D4\\cd.ico","filesize": 0,"modified":"2005-10-04T15:23:00-04:00","errors": "empty source","matches": [{"ns":"wikidata","id":"Q28205580","format":"OS/2 Icon","URI":"http://www.wikidata.org/entity/Q28205580","mime":"","basis":"extension match ico","source":"","warning":""},{"ns":"wikidata","id":"Q28206771","format":"OS/2 Bitmap Array","URI":"http://www.wikidata.org/entity/Q28206771","mime":"","basis":"extension match ico","source":"","warning":""},{"ns":"wikidata","id":"Q28205626","format":"Sun icon","URI":"http://www.wikidata.org/entity/Q28205626","mime":"","basis":"extension match ico","source":"","warning":""},{"ns":"wikidata","id":"Q729366","format":"ICO","URI":"http://www.wikidata.org/entity/Q729366","mime":"image/vnd.microsoft.icon","basis":"extension match ico","source":"","warning":""}]}]}
